sources/controller.sv
module controller(
  input logic clk,rst,
  input logic val_in,rdy_out,
  output logic rdy_in,val_out
);

//State Defination
typedef enum {idle,s0,s1,s2,s3} state_name;
state_name state_reg, state_next;

//Present State Logic
always_ff @(posedge clk)
begin
  if(rst)
    state_reg <= idle;
  else
    state_reg <= state_next;
end

//Next State Logic
always_comb 
begin
  unique case (state_reg)
  idle:
    state_next = s0;
  s0:
    state_next = s1;
  s1:
    state_next = s2;
  s2:
    state_next = s3;
  s3:
    state_next = s0;
  endcase
end

//Output Logic
always_comb
begin
    if (state_reg == idle)
    begin
        rdy_in  = 1'b0;
        val_out = 1'b0;
    end
    if(state_reg == s0)
    begin
        rdy_in  = 1'b1;
        val_out = 1'b0;
    end
    else if(state_reg == s3)
    begin
        rdy_in  = 1'b0;
        val_out = 1'b1;
    end
    else
    begin
        rdy_in  = 1'b0;
        val_out = 1'b0;
    end
end

// Dump waves
initial 
begin
  $dumpfile("dump.vcd");   // Specifies the name of the dump file
  $dumpvars(1, controller);     // Dumps the variables of the adder module
end

endmodule

verification/test_controller/dump.vcd
$date
	Sun May 26 06:55:53 2024
$end

$version
	Synopsys VCS version S-2021.09-SP2-5_Full64
$end

$timescale
	1ps
$end

$comment Csum: 1 6e4904cfaf3d264e $end


$scope module controller $end
$var reg 1 ! clk $end
$var reg 1 " rst $end
$var reg 1 # val_in $end
$var reg 1 $ rdy_out $end
$var reg 1 % rdy_in $end
$var reg 1 & val_out $end
$var reg 32 ' state_reg [31:0] $end
$var reg 32 ( state_next [31:0] $end
$upscope $end

$enddefinitions $end

#0
$dumpvars
0%
0&
b00000000000000000000000000000001 (
b00000000000000000000000000000000 '
1!
1"
x#
x$
$end
#1
0!
#2
1!
1$
1#
0"
#3
0!
#4
1!
b00000000000000000000000000000001 '
b00000000000000000000000000000010 (
1%
#5
0!
#6
1!
b00000000000000000000000000000010 '
b00000000000000000000000000000011 (
0%
#7
0!
#8
1!
b00000000000000000000000000000011 '
b00000000000000000000000000000100 (
#9
0!
#10
1!
b00000000000000000000000000000100 '
b00000000000000000000000000000001 (
1&
#11
0!
#12
1!
b00000000000000000000000000000001 '
b00000000000000000000000000000010 (
0&
1%
#13
0!
#14
1!
b00000000000000000000000000000010 '
b00000000000000000000000000000011 (
0%
#15
0!
#16
1!
b00000000000000000000000000000011 '
b00000000000000000000000000000100 (
#17
0!
#18
1!
b00000000000000000000000000000100 '
b00000000000000000000000000000001 (
1&
#19
0!
#20
1!
b00000000000000000000000000000001 '
b00000000000000000000000000000010 (
0&
1%
